devctx/__init__.py
devctx/__main__.py
devctx/cli.py
devctx/config.py
devctx/fuzzy.py
devctx/github_client.py
devctx/workspace.py
devctx-0.1.0.dist-info/METADATA
devctx-0.1.0.dist-info/WHEEL
devctx-0.1.0.dist-info/entry_points.txt
devctx-0.1.0.dist-info/licenses/LICENSE
devctx-0.1.0.dist-info/RECORD
