Metadata-Version: 2.4
Name: devctx
Version: 0.1.0
Summary: A CLI tool for creating temporary monorepos from GitHub repositories
Project-URL: Homepage, https://github.com/PragmaticMachineLearning/devctx
Project-URL: Repository, https://github.com/PragmaticMachineLearning/devctx
Project-URL: Issues, https://github.com/PragmaticMachineLearning/devctx/issues
Author-email: Madison May <madison@indico.io>
License: MIT
License-File: LICENSE
Keywords: cli,git,github,monorepo,workspace
Classifier: Development Status :: 3 - Alpha
Classifier: Intended Audience :: Developers
Classifier: License :: OSI Approved :: MIT License
Classifier: Programming Language :: Python :: 3
Classifier: Programming Language :: Python :: 3.8
Classifier: Programming Language :: Python :: 3.9
Classifier: Programming Language :: Python :: 3.10
Classifier: Programming Language :: Python :: 3.11
Classifier: Programming Language :: Python :: 3.12
Classifier: Topic :: Software Development
Classifier: Topic :: System :: Systems Administration
Requires-Python: >=3.8
Requires-Dist: click>=8.1.0
Requires-Dist: pydantic>=2.0.0
Requires-Dist: pygithub>=2.1.0
Requires-Dist: rapidfuzz>=3.0.0
Requires-Dist: rich>=13.0.0
